README.md
setup.py
treeHandler/__init__.py
treeHandler/treeHandler.py
treeHandler.egg-info/PKG-INFO
treeHandler.egg-info/SOURCES.txt
treeHandler.egg-info/dependency_links.txt
treeHandler.egg-info/not-zip-safe
treeHandler.egg-info/top_level.txt