Metadata-Version: 2.1
Name: treeHandler
Version: 1.4
Summary: Python OS wrapper to grab all/specific files from all the subdirectories
Home-page: https://github.com/Sreekiranar/treeHandler.git
Author-email: sreekiranar@gmail.com
License: MIT
Platform: UNKNOWN
